CHANGES.rst
CONTRIBUTORS.rst
DEVELOP.rst
LICENSE.GPL
LICENSE.rst
LINKS.rst
MANIFEST.in
README.rst
SPECS.rst
setup.py
docs/index.rst
src/fhir/__init__.py
src/fhir.heart.egg-info/PKG-INFO
src/fhir.heart.egg-info/SOURCES.txt
src/fhir.heart.egg-info/dependency_links.txt
src/fhir.heart.egg-info/entry_points.txt
src/fhir.heart.egg-info/namespace_packages.txt
src/fhir.heart.egg-info/not-zip-safe
src/fhir.heart.egg-info/requires.txt
src/fhir.heart.egg-info/top_level.txt
src/fhir/heart/__init__.py
src/fhir/heart/configure.zcml
src/fhir/heart/interfaces.py
src/fhir/heart/permissions.zcml
src/fhir/heart/setuphandlers.py
src/fhir/heart/testing.py
src/fhir/heart/upgrades.py
src/fhir/heart/upgrades.zcml
src/fhir/heart/vocabularies.zcml
src/fhir/heart/zcml.py
src/fhir/heart/browser/__init__.py
src/fhir/heart/browser/configure.zcml
src/fhir/heart/browser/overrides/.gitkeep
src/fhir/heart/browser/static/.gitkeep
src/fhir/heart/locales/fhir.heart.pot
src/fhir/heart/locales/update.sh
src/fhir/heart/profiles/default/browserlayer.xml
src/fhir/heart/profiles/default/metadata.xml
src/fhir/heart/profiles/default/registry.xml
src/fhir/heart/profiles/default/rolemap.xml
src/fhir/heart/profiles/uninstall/browserlayer.xml
src/fhir/heart/schema/__init__.py
src/fhir/heart/schema/oauth_application.py
src/fhir/heart/schema/oauth_token_code.py
src/fhir/heart/schema/user.py
src/fhir/heart/tests/__init__.py
src/fhir/heart/tests/test_robot.py
src/fhir/heart/tests/test_setup.py
src/fhir/heart/tests/robot/test_example.robot