Metadata-Version: 1.1
Name: fhir.heart
Version: 1.0.0a1
Summary: Health Relationship Trust Profile (HEART) implementation for FHIR (Fast Healthcare Interoperability Resources) compliance for Healthcare System.
Home-page: https://pypi.python.org/pypi/fhir.heart
Author: Md Nazrul Islam
Author-email: email2nazrul@gmail.com
License: GPL version 2
Keywords: Python Plone oauth2 fhir openid
Platform: UNKNOWN
Classifier: Development Status :: 3 - Alpha
Classifier: Environment :: Web Environment
Classifier: Framework :: Plone
Classifier: Framework :: Plone :: 4.3
Classifier: Framework :: Plone :: 5.0
Classifier: Framework :: Plone :: 5.1
Classifier: Programming Language :: Python
Classifier: Programming Language :: Python :: 2.7
Classifier: Programming Language :: Python :: 3.4
Classifier: Programming Language :: Python :: 3.5
Classifier: Programming Language :: Python :: 3.6
Classifier: Programming Language :: Python :: 3.7
Classifier: Intended Audience :: Healthcare Industry
Classifier: Intended Audience :: Information Technology
Classifier: Operating System :: OS Independent
Classifier: License :: OSI Approved :: GNU General Public License v2 (GPLv2)
